PyFileDownloader/PyFileDownloader.py
PyFileDownloader/__init__.py
PyFileDownloader-1.2.0.dist-info/LICENSE
PyFileDownloader-1.2.0.dist-info/METADATA
PyFileDownloader-1.2.0.dist-info/WHEEL
PyFileDownloader-1.2.0.dist-info/top_level.txt
PyFileDownloader-1.2.0.dist-info/RECORD
