Metadata-Version: 2.1
Name: PyFileDownloader
Version: 1.2.0
Summary: A Python module to download any file-type from the internet.
Home-page: https://github.com/NotCookey/PyFileDownloader
Author: NotCookey
Author-email: kanao.nishimiya@gmail.com
License: UNKNOWN
Keywords: python,file,stream,download,downloader,file downloader,requests,save file,download file
Platform: UNKNOWN
Classifier: Programming Language :: Python :: 3
Classifier: Operating System :: Unix
Classifier: Operating System :: MacOS :: MacOS X
Classifier: Operating System :: Microsoft :: Windows
Requires-Dist: werkzeug
